BitlyAPI/__init__.py
BitlyAPI/exceptions.py
BitlyAPI/model.py
bitly_api_python-1.0.3.dist-info/LICENSE
bitly_api_python-1.0.3.dist-info/METADATA
bitly_api_python-1.0.3.dist-info/WHEEL
bitly_api_python-1.0.3.dist-info/top_level.txt
bitly_api_python-1.0.3.dist-info/RECORD
