Metadata-Version: 2.1
Name: bitly-api-python
Version: 1.0.3
Summary: Wrapper for [Bitly API](https://api.ksprojects.me/bitly)
Home-page: https://github.com/Krishna-Singhal/bitly-api-python
Author: Krishna-Singhal
Author-email: ylikehits3@gmail.com
Project-URL: Bug Tracker, https://github.com/Krishna-Singhal/bitly-api-python/issues
Classifier: Programming Language :: Python :: 3
Classifier: License :: OSI Approved :: GNU General Public License v3 (GPLv3)
Classifier: Operating System :: OS Independent
Requires-Python: >=3.6
License-File: LICENSE
Requires-Dist: requests
